setup.py
janrain_datalib/__init__.py
janrain_datalib/_version.py
janrain_datalib/app.py
janrain_datalib/client.py
janrain_datalib/clientsettings.py
janrain_datalib/defaultsettings.py
janrain_datalib/exceptions.py
janrain_datalib/schema.py
janrain_datalib/schemaattributes.py
janrain_datalib/schemarecord.py
janrain_datalib/schemarecords.py
janrain_datalib/schemarules.py
janrain_datalib/utils.py
janrain_datalib.egg-info/PKG-INFO
janrain_datalib.egg-info/SOURCES.txt
janrain_datalib.egg-info/dependency_links.txt
janrain_datalib.egg-info/requires.txt
janrain_datalib.egg-info/top_level.txt