Metadata-Version: 1.0
Name: janrain-datalib
Version: 0.1.7
Summary: Janrain Capture Data Library
Home-page: https://github.com/janrain/janrain-python-datalib
Author: UNKNOWN
Author-email: UNKNOWN
License: UNKNOWN
Platform: UNKNOWN
